LICENSE.txt
MANIFEST.in
README.rst
setup.cfg
setup.py
django_adtools/__init__.py
django_adtools/ad_tools.py
django_adtools/admin.py
django_adtools/apps.py
django_adtools/discover_dc.py
django_adtools/models.py
django_adtools/tests.py
django_adtools/version.py
django_adtools/views.py
django_adtools.egg-info/PKG-INFO
django_adtools.egg-info/SOURCES.txt
django_adtools.egg-info/dependency_links.txt
django_adtools.egg-info/entry_points.txt
django_adtools.egg-info/requires.txt
django_adtools.egg-info/top_level.txt
django_adtools/management/__init__.py
django_adtools/management/commands/__init__.py
django_adtools/management/commands/build_package.py
django_adtools/management/commands/discover.py
django_adtools/management/commands/makedoc.py
django_adtools/management/commands/upload_package.py