Metadata-Version: 2.1
Name: django-adtools
Version: 1.7
Summary: UNKNOWN
Home-page: https://github.com/shmakovpn/django_adtools
Author: shmakovpn
Author-email: shmakovpn@yandex.ru
License: UNKNOWN
Download-URL: https://github.com/shmakovpn/django_ocr_server/archive/1.7.zip
Platform: UNKNOWN
